odoo/addons/fiscal_epos_print/README.rst
odoo/addons/fiscal_epos_print/__init__.py
odoo/addons/fiscal_epos_print/__manifest__.py
odoo/addons/fiscal_epos_print/i18n/fiscal_epos_print.pot
odoo/addons/fiscal_epos_print/i18n/it.po
odoo/addons/fiscal_epos_print/migrations/12.0.2.0.0/post-fiscal_epos_disable_reprint.py
odoo/addons/fiscal_epos_print/models/__init__.py
odoo/addons/fiscal_epos_print/models/account.py
odoo/addons/fiscal_epos_print/models/account_journal.py
odoo/addons/fiscal_epos_print/models/point_of_sale.py
odoo/addons/fiscal_epos_print/models/pos_order.py
odoo/addons/fiscal_epos_print/readme/CONFIGURE.rst
odoo/addons/fiscal_epos_print/readme/CONTRIBUTORS.rst
odoo/addons/fiscal_epos_print/readme/DESCRIPTION.rst
odoo/addons/fiscal_epos_print/readme/ROADMAP.rst
odoo/addons/fiscal_epos_print/static/description/icon.png
odoo/addons/fiscal_epos_print/static/description/index.html
odoo/addons/fiscal_epos_print/static/lib/fiscalprint/fiscalprint.js
odoo/addons/fiscal_epos_print/static/lib/pikaday/pikaday.min.css
odoo/addons/fiscal_epos_print/static/lib/pikaday/pikaday.min.js
odoo/addons/fiscal_epos_print/static/src/css/pos.css
odoo/addons/fiscal_epos_print/static/src/img/X.svg
odoo/addons/fiscal_epos_print/static/src/img/Z.svg
odoo/addons/fiscal_epos_print/static/src/img/ade-logo.svg
odoo/addons/fiscal_epos_print/static/src/img/cashdrawer.svg
odoo/addons/fiscal_epos_print/static/src/img/epos.svg
odoo/addons/fiscal_epos_print/static/src/img/reprint.svg
odoo/addons/fiscal_epos_print/static/src/js/chrome.js
odoo/addons/fiscal_epos_print/static/src/js/epson_epos_print.js
odoo/addons/fiscal_epos_print/static/src/js/models.js
odoo/addons/fiscal_epos_print/static/src/js/popups.js
odoo/addons/fiscal_epos_print/static/src/js/pos_order_mgmt.js
odoo/addons/fiscal_epos_print/static/src/js/screens.js
odoo/addons/fiscal_epos_print/static/src/xml/lottery.xml
odoo/addons/fiscal_epos_print/static/src/xml/pos.xml
odoo/addons/fiscal_epos_print/views/account.xml
odoo12_addon_fiscal_epos_print-12.0.2.0.3.dist-info/METADATA
odoo12_addon_fiscal_epos_print-12.0.2.0.3.dist-info/WHEEL
odoo12_addon_fiscal_epos_print-12.0.2.0.3.dist-info/top_level.txt
odoo12_addon_fiscal_epos_print-12.0.2.0.3.dist-info/RECORD
