Metadata-Version: 2.1
Name: odoo12-addon-fiscal_epos_print
Version: 12.0.2.0.3
Summary: ePOS-Print XML Fiscal Printer Driver - Stampanti Epson compatibili: FP81II, FP90III
Home-page: https://github.com/OCA/l10n-italy/tree/12.0/fiscal_epos_print
Author: Odoo Community Association (OCA), Agile Business Group, Leonardo Donelli, TAKOBI, Level Prime Srl
Author-email: support@odoo-community.org
License: AGPL-3
Classifier: Programming Language :: Python
Classifier: Framework :: Odoo
Classifier: Framework :: Odoo :: 12.0
Classifier: License :: OSI Approved :: GNU Affero General Public License v3
Requires-Python: >=3.5
Requires-Dist: odoo12-addon-pos-order-mgmt
Requires-Dist: odoo<12.1dev,>=12.0a
